keyrock_math/__init__.py
keyrock_math/distribution/__init__.py
keyrock_math/distribution/analytic.py
keyrock_math/distribution/beta.py
keyrock_math/distribution/constant.py
keyrock_math/distribution/distribution.py
keyrock_math/distribution/gamma.py
keyrock_math/distribution/log_normal.py
keyrock_math/distribution/logistic.py
keyrock_math/distribution/normal.py
keyrock_math/distribution/skew_normal.py
keyrock_math/distribution/test_distribution.py
keyrock_math/distribution/uniform.py
keyrock_math/distribution/weibull.py
keyrock_math-2024.2.15.1117.dist-info/METADATA
keyrock_math-2024.2.15.1117.dist-info/WHEEL
keyrock_math-2024.2.15.1117.dist-info/top_level.txt
keyrock_math-2024.2.15.1117.dist-info/RECORD
