Metadata-Version: 2.1
Name: keyrock-math
Version: 2024.2.15.1117
Requires-Dist: keyrock-model
Requires-Dist: numpy ==1.26.4
Requires-Dist: scipy ==1.12.0
